chinillablspy.cp310-win_amd64.pyd
mpir.dll
mpir_broadwell.dll
mpir_broadwell_avx.dll
mpir_bulldozer.dll
mpir_gc.dll
mpir_haswell.dll
mpir_piledriver.dll
mpir_sandybridge.dll
mpir_skylake_avx.dll
chinillablspy-1.0.16.dist-info/LICENSE
chinillablspy-1.0.16.dist-info/METADATA
chinillablspy-1.0.16.dist-info/RECORD
chinillablspy-1.0.16.dist-info/top_level.txt
chinillablspy-1.0.16.dist-info/WHEEL
