Metadata-Version: 2.1
Name: chinillablspy
Version: 1.0.16
Summary: BLS signatures in c++ (with python bindings)
Home-page: https://github.com/Chinilla/bls-signatures
Author: Mariano Sorgente
Author-email: mariano@chinilla.com
Requires-Python: >=3.7
License-File: LICENSE
Requires-Dist: pybind11 (>=2.10.0)
